veles/__init__.py
veles/device/__init__.py
veles/device/find.py
veles/device/generic.py
veles/device/modbus.py
veles/device/sensor_wired.py
veles-0.1.0.dist-info/LICENSE
veles-0.1.0.dist-info/METADATA
veles-0.1.0.dist-info/WHEEL
veles-0.1.0.dist-info/top_level.txt
veles-0.1.0.dist-info/RECORD
