Metadata-Version: 2.1
Name: veles
Version: 0.1.0
Summary: Python package for VelesLabs devices
Home-page: https://gitea.veleslabs.org/veles_labs/pyveles
Author: VelesLabs
Author-email: info@veleslabs.org
Classifier: Programming Language :: Python :: 3
Classifier: License :: OSI Approved :: MIT License
Classifier: Operating System :: OS Independent
Requires-Python: >=3.6
License-File: LICENSE
Requires-Dist: minimalmodbus (>=2.0.1)
Requires-Dist: pyserial (>=3.5)
